pytools/__init__.py
pytools/py.typed
pytools/api/__init__.py
pytools/api/_all.py
pytools/api/_alltracker.py
pytools/api/_api.py
pytools/api/_decorators.py
pytools/api/_doc_validator.py
pytools/api/_introspection.py
pytools/api/_missing.py
pytools/api/doc/__init__.py
pytools/api/doc/_doc.py
pytools/asyncio/__init__.py
pytools/asyncio/_asyncio.py
pytools/data/__init__.py
pytools/data/_linkage.py
pytools/data/_matrix.py
pytools/data/_simulation.py
pytools/data/linkage/__init__.py
pytools/data/linkage/_linkage.py
pytools/data/taxonomy/__init__.py
pytools/data/taxonomy/_category.py
pytools/data/taxonomy/_taxonomy.py
pytools/expression/__init__.py
pytools/expression/_expression.py
pytools/expression/_initparams.py
pytools/expression/atomic/__init__.py
pytools/expression/atomic/_atomic.py
pytools/expression/base/__init__.py
pytools/expression/base/_base.py
pytools/expression/composite/__init__.py
pytools/expression/composite/_composite.py
pytools/expression/composite/base/__init__.py
pytools/expression/composite/base/_base.py
pytools/expression/formatter/__init__.py
pytools/expression/formatter/_python.py
pytools/expression/operator/__init__.py
pytools/expression/operator/_operator.py
pytools/expression/repr/__init__.py
pytools/expression/repr/_repr.py
pytools/fit/__init__.py
pytools/fit/_fit.py
pytools/http/__init__.py
pytools/http/_http.py
pytools/meta/__init__.py
pytools/meta/_meta.py
pytools/parallelization/__init__.py
pytools/parallelization/_parallelization.py
pytools/repr/__init__.py
pytools/repr/_dict.py
pytools/sphinx/__init__.py
pytools/sphinx/_sphinx.py
pytools/sphinx/util/__init__.py
pytools/sphinx/util/_util.py
pytools/text/__init__.py
pytools/text/_strings.py
pytools/text/_template.py
pytools/text/_text.py
pytools/typing/__init__.py
pytools/typing/_typing.py
pytools/viz/__init__.py
pytools/viz/_html.py
pytools/viz/_matplot.py
pytools/viz/_notebook.py
pytools/viz/_text.py
pytools/viz/_viz.py
pytools/viz/color/__init__.py
pytools/viz/color/_color.py
gamma_pytools-3.0.2.dist-info/LICENSE
gamma_pytools-3.0.2.dist-info/WHEEL
gamma_pytools-3.0.2.dist-info/METADATA
gamma_pytools-3.0.2.dist-info/RECORD
