Metadata-Version: 2.1
Name: gamma-pytools
Version: 3.0.2
Summary: A collection of Python extensions and tools used in BCG GAMMA's open-source libraries.
Home-page: https://github.com/BCG-X-Official/pytools
License: Apache Software License v2.0
Author: Boston Consulting Group (BCG)
Requires-Python: >=3.10,<4a
Classifier: Development Status :: 5 - Production/Stable
Classifier: Intended Audience :: Science/Research
Classifier: License :: OSI Approved :: Apache Software License
Classifier: Operating System :: MacOS
Classifier: Operating System :: Microsoft :: Windows
Classifier: Operating System :: POSIX :: Linux
Classifier: Operating System :: Unix
Classifier: Programming Language :: Python
Classifier: Programming Language :: Python :: 3
Classifier: Programming Language :: Python :: 3.10
Classifier: Topic :: Scientific/Engineering
Requires-Dist: joblib            ~=1.0
Requires-Dist: matplotlib        ~=3.6
Requires-Dist: numpy             >=1.23,<3a
Requires-Dist: pandas            >=1.5
Requires-Dist: scipy             ~=1.9
Requires-Dist: typing_inspect    ~=0.7
Requires-Dist: typing_extensions ~=4.0
Requires-Dist: sphinx ~= 4.5 ; extra == "docs"
Requires-Dist: sphinx-autodoc-typehints ~= 1.19 ; extra == "docs"
Requires-Dist: pydata-sphinx-theme ~= 0.8.1 ; extra == "docs"
Requires-Dist: jinja2 ~= 2.11 ; extra == "docs"
Requires-Dist: nbsphinx ~= 0.8.9 ; extra == "docs"
Requires-Dist: jupyter == 1 ; extra == "docs"
Requires-Dist: docutils ~= 0.17 ; extra == "docs"
Requires-Dist: xlrd ~= 1.2 ; extra == "docs"
Requires-Dist: m2r ~= 0.2 ; extra == "docs"
Requires-Dist: mypy ~= 1.10 ; extra == "docs"
Requires-Dist: pytest ~= 7.1 ; extra == "testing"
Requires-Dist: pytest-cov ~= 2.12 ; extra == "testing"
Project-URL: Documentation, https://bcg-x-official.github.io/pytools/
Project-URL: Repository, https://github.com/BCG-X-Official/pytools
Provides-Extra: docs
Provides-Extra: testing
